veribiota/__init__.py
veribiota/adapter/__init__.py
veribiota/adapter/cli.py
veribiota/adapter/lean_check.py
veribiota/adapter/preflight.py
veribiota/adapter/schema.py
veribiota/adapter/suite_codegen.py
veribiota-0.1.0.dist-info/licenses/LICENSE
veribiota-0.1.0.dist-info/licenses/NOTICE
veribiota-0.1.0.dist-info/METADATA
veribiota-0.1.0.dist-info/WHEEL
veribiota-0.1.0.dist-info/entry_points.txt
veribiota-0.1.0.dist-info/top_level.txt
veribiota-0.1.0.dist-info/RECORD
