Metadata-Version: 2.4
Name: veribiota
Version: 0.1.0
Summary: Python adapter and CLI for VeriBiota EditDAG JSON normalization and Lean suite generation.
Author: VeriBiota developers
License: Apache-2.0
Classifier: Programming Language :: Python :: 3
Classifier: Programming Language :: Python :: 3 :: Only
Classifier: License :: OSI Approved :: Apache Software License
Classifier: Intended Audience :: Science/Research
Classifier: Topic :: Scientific/Engineering :: Bio-Informatics
Requires-Python: >=3.10
License-File: LICENSE
License-File: NOTICE
Dynamic: license-file
